kg-search
setup.cfg
setup.py
kg_search/__init__.py
kg_search/api.py
kg_search/ld.py
kg_search/metadata.json
kg_search/search.py
kg_search.egg-info/PKG-INFO
kg_search.egg-info/SOURCES.txt
kg_search.egg-info/dependency_links.txt
kg_search.egg-info/requires.txt
kg_search.egg-info/top_level.txt