Metadata-Version: 1.1
Name: kg-search
Version: 0.1.10
Summary: A REST API wrapper for Google Knowledge Graph
Home-page: https://github.com/fserena/kg-search
Author: Fernando Serena
Author-email: fserena@fi.upm.es
License: Apache 2
Download-URL: https://github.com/fserena/kg-search/tarball/0.1.10
Keywords: knowledge graph,wikidata
Platform: UNKNOWN
